{
    "events": {
        "CimConnectEtcdFailure": {
            "eventType": "COMMUNICATION",
            "perceivedSeverity": "CRITICAL",
            "probableCause": "etcd communication failure",
            "specificProblem": "CIM unable to establish connection to etcd",
            "rootCauseIndicator": "",
            "trendIndication": "",
            "correlatedNotifications": "",
            "additionalText": "",
            "proposedRepairAction": "",
            "serviceTypeAffected": "MULTIPLE",
            "alarmHierarchy": "Independent",
            "classification": "Outage",
            "alarmType": "Communications alarm"
        },
        "RoleAssignmentStatus": {
            "eventType": "HA_ROLE_ASSIGNMENT",
            "perceivedSeverity": "INFO",
            "probableCause": "Role assignment status received for HA operation.",
            "specificProblem": "Role assignment status received for HA operation.",
            "rootCauseIndicator": "",
            "trendIndication": "",
            "correlatedNotifications": "",
            "additionalText": "",
            "proposedRepairAction": "",
            "serviceTypeAffected": "NONE",
            "alarmHierarchy": "Independent",
            "classification": "Notification",
            "alarmType": ""
        },
        "HAMonitoringFailure": {
            "eventType": "HA_MONITORING",
            "perceivedSeverity": "MAJOR",
            "probableCause": "HA Failed To Monitor Application uS",
            "specificProblem": "HA Failed To Monitor Application uS",
            "rootCauseIndicator": "",
            "trendIndication": "",
            "correlatedNotifications": "",
            "additionalText": "",
            "proposedRepairAction": "",
            "serviceTypeAffected": "NONE",
            "alarmHierarchy": "Independent",
            "classification": "Deterioration",
            "alarmType": "Process error alarm"
        },
        "LmaasTCPFailure": {
            "eventType": "COMMUNICATION",
            "perceivedSeverity": "MAJOR",
            "probableCause": "TCP connection failure towards fluent-bit onbserved in LMaaS",
            "specificProblem": "TCP connection failure towards fluent-bit onbserved in LMaaS",
            "rootCauseIndicator": "",
            "trendIndication": "",
            "correlatedNotifications": "",
            "additionalText": "",
            "proposedRepairAction": "Verify fluent-bit is running.",
            "serviceTypeAffected": "MULTIPLE",
            "alarmHierarchy": "Independent",
            "classification": "Deterioration",
            "alarmType": "Service quality alarm"
        },
        "CimCommitConfigSuccess": {
            "eventType": "COMMIT_CONFIG",
            "perceivedSeverity": "INFO",
            "probableCause": "A commit-config operation towards etcd is successful",
            "specificProblem": "A commit-config operation towards etcd is successful",
            "rootCauseIndicator": "",
            "trendIndication": "",
            "correlatedNotifications": "",
            "additionalText": "",
            "proposedRepairAction": "",
            "serviceTypeAffected": "NONE",
            "alarmHierarchy": "Independent",
            "classification": "Notification",
            "alarmType": ""
        },
        "CimCommitConfigFailure": {
            "eventType": "COMMIT_CONFIG",
            "perceivedSeverity": "MAJOR",
            "probableCause": "A commit-config operation failed towards etcd",
            "specificProblem": "A commit-config operation failed towards etcd",
            "rootCauseIndicator": "",
            "trendIndication": "",
            "correlatedNotifications": "",
            "additionalText": "",
            "proposedRepairAction": "",
            "serviceTypeAffected": "MULTIPLE",
            "alarmHierarchy": "Independent",
            "classification": "Outage",
            "alarmType": "Communications alarm"
        },
        "CimConfigUpdateSuccess": {
            "eventType": "CONFIG_UPDATE",
            "perceivedSeverity": "INFO",
            "probableCause": "Successfully updated CIM configuration",
            "specificProblem": "Successfully updated CIM configuration",
            "rootCauseIndicator": "",
            "trendIndication": "",
            "correlatedNotifications": "",
            "additionalText": "",
            "proposedRepairAction": "",
            "serviceTypeAffected": "NONE",
            "alarmHierarchy": "Independent",
            "classification": "Notification",
            "alarmType": ""
        },
        "CimConfigUpdateFailure": {
            "eventType": "CONFIG_UPDATE",
            "perceivedSeverity": "MAJOR",
            "probableCause": "Failure updating CIM configuration",
            "specificProblem": "Failure updating CIM configuration",
            "rootCauseIndicator": "",
            "trendIndication": "",
            "correlatedNotifications": "",
            "additionalText": "",
            "proposedRepairAction": "",
            "serviceTypeAffected": "MULTIPLE",
            "alarmHierarchy": "Independent",
            "classification": "Outage",
            "alarmType": "Communications alarm"
        }
    }
}
